comet_common/__init__.py
comet_common/comet_exceptions.py
comet_common/comet_input_google_pubsub.py
comet_common/comet_parser_detectify.py
comet_common/comet_parser_forseti.py
comet_common-4.3.0.dist-info/LICENSE
comet_common-4.3.0.dist-info/METADATA
comet_common-4.3.0.dist-info/WHEEL
comet_common-4.3.0.dist-info/top_level.txt
comet_common-4.3.0.dist-info/RECORD
