Metadata-Version: 2.1
Name: comet-common
Version: 4.3.0
Summary: Comet Distributed Security Notification Framework
Home-page: https://github.com/spotify/comet-common
Author: Spotify Platform Security
Author-email: wasabi@spotify.com
License: UNKNOWN
Platform: UNKNOWN
Classifier: Development Status :: 5 - Production/Stable
Classifier: Programming Language :: Python
Classifier: Programming Language :: Python :: 3
Classifier: Programming Language :: Python :: 3.6
Classifier: Programming Language :: Python :: 3.7
Classifier: Programming Language :: Python :: 3.8
Classifier: Programming Language :: Python :: 3.9
Requires-Dist: comet-core (>2)
Requires-Dist: google-cloud-pubsub (<2,>1)
Requires-Dist: marshmallow (<4,>3)
